hamsay/__init__.py
hamsay/__main__.py
hamsay/hamsters/__init__.py
hamsay/hamsters/hams.py
hamsay/help/__init__.py
hamsay/help/help.py
hamsay/main.py
hamsay-0.1.1.dist-info/entry_points.txt
hamsay-0.1.1.dist-info/WHEEL
hamsay-0.1.1.dist-info/METADATA
hamsay-0.1.1.dist-info/RECORD
