Metadata-Version: 2.1
Name: hamsay
Version: 0.1.1
Summary: Hamsters talking
Home-page: https://github.com/sebastardo/HamSay
License: MIT
Author: Sebastardo
Author-email: sebastardo@outlook.com
Requires-Python: >=3.8,<4.0
Classifier: License :: OSI Approved :: MIT License
Classifier: Programming Language :: Python :: 3
Classifier: Programming Language :: Python :: 3.8
Classifier: Programming Language :: Python :: 3.9
Classifier: Programming Language :: Python :: 3.10
Project-URL: Repository, https://github.com/sebastardo/HamSay
